xmpy_datarecorder/__init__.py
xmpy_datarecorder/数据记录引擎.py
xmpy_datarecorder-1.0.1.dist-info/METADATA
xmpy_datarecorder-1.0.1.dist-info/WHEEL
xmpy_datarecorder-1.0.1.dist-info/licenses/LICENSE
xmpy_datarecorder-1.0.1.dist-info/RECORD
